LICENSE
MANIFEST.in
README.md
setup.py
a10_openstack_lib/__init__.py
a10_openstack_lib.egg-info/PKG-INFO
a10_openstack_lib.egg-info/SOURCES.txt
a10_openstack_lib.egg-info/dependency_links.txt
a10_openstack_lib.egg-info/top_level.txt
a10_openstack_lib/resources/__init__.py
a10_openstack_lib/resources/a10_certificate.py
a10_openstack_lib/resources/a10_device_instance.py
a10_openstack_lib/resources/a10_scaling_group.py
a10_openstack_lib/resources/template.py
a10_openstack_lib/resources/validators.py
a10_openstack_lib/tests/__init__.py
a10_openstack_lib/tests/test_resources.py