Metadata-Version: 1.1
Name: a10-openstack-lib
Version: 0.2.1
Summary: A10 Networks Common OpenStack Library
Home-page: https://github.com/a10networks/a10-openstack-lib
Author: A10 Networks
Author-email: dougw@a10networks.com
License: Apache
Keywords: a10 adc slb load balancer openstack neutron lbaas cli
Platform: UNKNOWN
Classifier: License :: OSI Approved :: Apache Software License
Classifier: Operating System :: POSIX
Classifier: Programming Language :: Python
Classifier: Programming Language :: Python :: 2.7
Classifier: Topic :: Internet
